{
    "bar": {
        "random": false,
        "category": "ambience",
        "tracks": [
            {
                "path": "bar.mp3",
                "loop": 0
            }
        ]
    },
    "barfight": {
        "random": false,
        "category": "battle",
        "tracks": [
            {
                "path": "barfight.mp3",
                "loop": 0
            }
        ]
    },
    "dualofthefates": {
        "random": false,
        "category": "battle",
        "tracks": [
            {
                "path": "Battle/John Williams - Dual of the Fates.mp3",
                "loop": -1
            }
        ]
    },
    "battleoftheheroes": {
        "random": false,
        "category": "battle",
        "tracks": [
            {
                "path": "Battle/John Williams - Battle of the Heroes.mp3",
                "loop": -1
            }
        ]
    },
    "fvictory": {
        "random": false,
        "category": "sfx",
        "tracks": [
            {
                "path": "sfx/fvictory.mp3",
                "loop": 0
            }
        ]
    },
    "victory": {
        "random": false,
        "category": "sfx",
        "tracks": [
            {
                "path": "sfx/victory.mp3",
                "loop": 0
            }
        ]
    },
    "battle": {
        "random": true,
        "category": "battle",
        "shuffle": true,
        "tracks": [
            {
                "path": "Battle/battle0.mp3",
                "loop": -1
            },
            {
                "path": "Battle/battle1.mp3",
                "loop": -1
            },
            {
                "path": "Battle/battle2.mp3",
                "loop": -1
            },
            {
                "path": "Battle/battle3.mp3",
                "loop": -1
            },
            {
                "path": "Battle/battle4.mp3",
                "loop": -1
            },
            {
                "path": "Battle/battle5.mp3",
                "loop": -1
            },
            {
                "path": "Battle/battle6.mp3",
                "loop": -1
            },
            {
                "path": "Battle/battle7.mp3",
                "loop": -1
            }
        ]
    },
    "cantena": {
        "random": false,
        "category": "ambience",
        "shuffle": true,
        "tracks": [
            {
                "path": "cantena/Party Until We See The Binary Suns.mp3",
                "loop": 0
            },
            {
                "path": "cantena/The Blue Trunks - Little Ortolans.mp3",
                "loop": 0
            },
            {
                "path": "cantena/The Blue Trunks Cantina Band - Corellian Swing.mp3",
                "loop": 0
            },
            {
                "path": "cantena/Cantina Band.mp3",
                "loop": 0
            }
        ]
    },
    "technocantina": {
        "random": false,
        "category": "ambience",
        "tracks": [
            {
                "path": "cantina/Techno Cantina.mp3",
                "loop": -1
            }
        ]
    },
    "calm": {
        "random": true,
        "category": "ambience",
        "shuffle": true,

        "tracks": [
            {
                "link": true,
                "path": "https://www.youtube.com/watch?v=TYkbTZQbygs",
                "loop": -1
            },
            {
                "link": true,
                "path": "https://www.youtube.com/watch?v=LgvKidqOP2U",
                "loop": -1
            }
        ]
    },
    "dark": {
        "random": true,
        "category": "ambience",
        "shuffle": true,

        "tracks": [
            {
                "link": true,
                "path": "https://www.youtube.com/watch?v=OI3xTWCUnJM",
                "loop": -1
            }
        ]
    },
    "mystery": {
        "random": true,
        "category": "ambience",
        "shuffle": true,

        "tracks": [
            {
                "link": true,
                "path": "https://www.youtube.com/watch?v=Ze-GLjOLflM",
                "loop": -1
            }
        ]
    },
    "tension": {
        "random": true,
        "category": "ambience",
        "shuffle": true,

        "tracks": [
            {
                "link": true,
                "path": "https://www.youtube.com/watch?v=JVMLoBbaTYI",
                "loop": -1
            }
        ]
    },
    "sadness": {
        "random": true,
        "category": "ambience",
        "shuffle": true,

        "tracks": [
            {
                "link": true,
                "path": "https://www.youtube.com/watch?v=_UyLkomRoiY",
                "loop": -1
            }
        ]
    }
}